cold_postman/__init__.py
cold_postman/__main__.py
cold_postman/postman.py
cold_postman/run.py
cold_postman/utils.py
cold_postman-0.1.9.dist-info/LICENSE
cold_postman-0.1.9.dist-info/METADATA
cold_postman-0.1.9.dist-info/WHEEL
cold_postman-0.1.9.dist-info/RECORD
