Metadata-Version: 2.1
Name: cold-postman
Version: 0.1.9
Summary: A postman helps you to send cold mails
Home-page: https://github.com/thisishugow/cold_postman
License: MIT
Author: thisishugow
Author-email: 59921505+thisishugow@users.noreply.github.com
Requires-Python: >=3.10,<4.0
Classifier: License :: OSI Approved :: MIT License
Classifier: Programming Language :: Python :: 3
Classifier: Programming Language :: Python :: 3.10
Classifier: Programming Language :: Python :: 3.11
Requires-Dist: markdown2 (>=2.4.10,<3.0.0)
Requires-Dist: pandas (>=2.1.0,<3.0.0)
Requires-Dist: pendulum (>=2.1.2,<3.0.0)
Requires-Dist: pyyaml (>=6.0.1,<7.0.0)
